server_check/__init__.py
server_check/bcolors.py
server_check/directadmin.py
server_check/exceptions.py
server_check/ftp.py
server_check/imap.py
server_check/php.py
server_check/phpmyadmin.py
server_check/pop3.py
server_check/roundcube.py
server_check/smtp.py
server_check/spamassassin.py
server_check-1.0.1.dist-info/DESCRIPTION.rst
server_check-1.0.1.dist-info/entry_points.txt
server_check-1.0.1.dist-info/METADATA
server_check-1.0.1.dist-info/metadata.json
server_check-1.0.1.dist-info/pbr.json
server_check-1.0.1.dist-info/RECORD
server_check-1.0.1.dist-info/top_level.txt
server_check-1.0.1.dist-info/WHEEL
