Metadata-Version: 2.0
Name: server-check
Version: 1.0.1
Summary: Check a DirectAdmin server to see if all components are (still) operating correctly
Home-page: https://github.com/exonet/scripts/server-check
Author: Rick van den Hof
Author-email: r.vandenhof@exonet.nl
License: MIT
Keywords: DirectAdmin check pop3 imap ftp smtp phpmyadmin mod_ruid2 spamassasassin roundcube
Platform: UNKNOWN
Classifier: Intended Audience :: Developers
Classifier: Intended Audience :: System Administrators
Classifier: Topic :: Utilities
Classifier: Environment :: Console
Classifier: License :: OSI Approved :: MIT License
Classifier: Programming Language :: Python :: 2.7
Classifier: Operating System :: OS Independent
Classifier: Development Status :: 4 - Beta
Requires-Dist: MySQL-python
Requires-Dist: requests
Requires-Dist: argparse
